images/__init__.py
images/color-palette.png
images/color-wheel.png
images/falling-star.png
images/fire.png
images/flag.png
images/rainbow.png
images/repeat.png
images/sparkles.png
images/speed.png
images/star.png
images/warning.png
images/wave.png
rpi_ws281x_hub/__init__.py
rpi_ws281x_hub/api.py
rpi_ws281x_hub/index.html
rpi_ws281x_hub/strip.py
rpi_ws281x_hub/tasks.py
rpi_ws281x_hub/variables.scss
rpi_ws281x_hub-1.0.3.dist-info/LICENSE
rpi_ws281x_hub-1.0.3.dist-info/METADATA
rpi_ws281x_hub-1.0.3.dist-info/WHEEL
rpi_ws281x_hub-1.0.3.dist-info/entry_points.txt
rpi_ws281x_hub-1.0.3.dist-info/top_level.txt
rpi_ws281x_hub-1.0.3.dist-info/RECORD
