Metadata-Version: 2.1
Name: rpi-ws281x-hub
Version: 1.0.3
Summary: Raspberry Pi - WS281x Led hub 🎨
Home-page: https://github.com/vrince/rpi-ws281x-hub
Author: Thomas Vincent
Author-email: vrince@gmail.com
License: MIT
Platform: UNKNOWN
Requires-Dist: appdirs (==1.4.4)
Requires-Dist: click (==8.0.3)
Requires-Dist: colour (==0.1.5)
Requires-Dist: easing-functions (==1.0.4)
Requires-Dist: fastapi (==0.70.0)
Requires-Dist: uvicorn[standard] (==0.15.0)
